[
  {
    "targets": [ "https://qa-status.baidu.com"],
    "labels": {
      "env": "QA",
      "job": "nginx status health check site.",
      "domain": "qa-status.baidu.com"
    }
  },
  {
    "targets": [ "https://www.baidu.com"],
    "labels": {
      "env": "Prod",
      "job": "website",
      "domain": "www.baidu.com"
    }
  },
  {
    "targets": [ "https://xsldevops.baidu.com/kubernetes/ha.svg"],
    "labels": {
      "env": "七牛云",
      "job": "七牛对象存储中的一个测试资源.",
      "domain": "xsldevops.baidu.com"
    }
  },
  {
    "targets": [ "http://192.168.64.84:3000"],
    "labels": {
      "env": "QA",
      "job": "grafana for QA environment.",
      "domain": "qa-grafana.xsl.link"
    }
  }
]
